LICENSE.txt
MANIFEST.in
README.rst
setup.py
masheryclient/__init__.py
masheryclient/jsonrpc.py
masheryclient/reporting.py
masheryclient.egg-info/PKG-INFO
masheryclient.egg-info/SOURCES.txt
masheryclient.egg-info/dependency_links.txt
masheryclient.egg-info/requires.txt
masheryclient.egg-info/top_level.txt