Metadata-Version: 1.1
Name: masheryclient
Version: 0.1.0
Summary: A simple Python client library for the Mashery API
Home-page: https://github.com/dasevilla/mashery-python
Author: Devin Sevilla
Author-email: dasevilla@gmail.com
License: UNKNOWN
Download-URL: https://github.com/dasevilla/mashery-python/tarball/master
Platform: UNKNOWN
Classifier: Development Status :: 3 - Alpha
Classifier: License :: OSI Approved :: MIT License
Classifier: Programming Language :: Python :: 2.7
